serde_bin_vec/__init__.py
serde_bin_vec/testing.py
serde_bin_vec-0.2.6.dist-info/WHEEL
serde_bin_vec-0.2.6.dist-info/METADATA
serde_bin_vec-0.2.6.dist-info/RECORD
